Metadata-Version: 1.0
Name: distributions-testupload-Udacity
Version: 0.1
Summary: Gaussian and Binomial distributions
Home-page: UNKNOWN
Author: Sebastiano
Author-email: UNKNOWN
License: UNKNOWN
Platform: UNKNOWN
